Metadata-Version: 1.0
Name: magickwand
Version: 0.1
Summary: Python bindings for ImageMagick's MagickWand 6.6.0
Home-page: http://digitalarchitekt.de/contributions/magickwand
Author: Oliver Berger
Author-email: oliver@digitalarchitekt.de
License: UNKNOWN
Keywords: ImageMagick MagickWand CDLL Binding
Platform: UNKNOWN
Classifier: Development Status :: 3 - Alpha
Classifier: Topic :: Multimedia :: Graphics
